<?xml version="1.0"?>
<!DOCTYPE struts PUBLIC
	"-//Apache Software Foundation//DTD Struts Configuration 2.1.7//EN"
	"http://struts.apache.org/dtds/struts-2.1.7.dtd">
<struts>
	<!-- 简单主题 -->
	<constant name="struts.ui.theme" value="simple"></constant>
	
	<!-- 开发模式 -->
	<constant name="struts.devMode" value="true"></constant>
	
	<package name="surveyParkPkg" namespace="/" extends="struts-default">
	
		<interceptors>
			<!-- 注册自定义登陆拦截器 -->
			<interceptor name="loginInterceptor" class="com.youngball.Gather.interceptor.LoginInterceptor"></interceptor>
			<interceptor-stack name="surveyparkStack">
				<interceptor-ref name="loginInterceptor"></interceptor-ref>
				<interceptor-ref name="defaultStack">
					<param name="modelDriven.refreshModelBeforeResult">true</param>
				</interceptor-ref>
			</interceptor-stack>
		</interceptors>
		
		<!-- 定义默认栈 -->
		<default-interceptor-ref name="surveyparkStack"></default-interceptor-ref>
	
		<!-- 全局结果 -->
		<global-results>
				<result name="logPage">/index.jsp</result>
		</global-results>
		
		<!-- regAcion -->
		<action name="RegAction_*" class="regAction" method="{1}">
			<result name="regPage">/reg.jsp</result>  
			<result name="success">/index.jsp</result>
			<result name="input">/reg.jsp</result>
		</action>
		
		<!-- loginAction -->
		<action name="LoginAction_*" class="loginAction" method="{1}">
			<result name="logPage">/index.jsp</result>
			<result name="success">/index.jsp</result>
			<result name="input">/index.jsp</result>
		</action>
		
		<!-- surveyAction -->
		<action name="SurveyAction_*" class="surveyAction" method="{1}">
			<result name="addSurveyPage">/designSurvey.jsp</result>
			<result name="mySurveysListPage">/mySurveyList.jsp</result>
			<result name="designSurveyPage">/designSurvey.jsp</result>
			<result name="editSurveyPage">/editSurvey.jsp</result>
			<!-- 设计调查 -->
			<result name="designSurveyAction" type="redirectAction">
				<param name="namespace"></param>
				<param name="actionName">SurveyAction_designSurvey</param>
				<param name="sid">${sid}</param>
			</result>
			<result name="logPage">/index.jsp</result>
			<result name="findMySurveysAction" type="redirectAction">
				<param name="namespace"></param>
				<param name="actionName">SurveyAction_mySurvey</param>
			</result>
			<result name="addLogoPage">/addLogo.jsp</result>
			<result name="input">${inputPage}</result>
			<interceptor-ref name="surveyparkStack">
				<!-- 限制文件 -->
				<param name="fileUpload.MaximumSize">60000</param>
				<param name="fileUpload.allowedExtensions">.jsp,.png,.gif</param>
				<param name="fileUpload.allowedTypes"></param>
				<param name="fileUpload.useActionMessageBundle">true</param>
			</interceptor-ref>
		</action>
		
	    <!-- PageAction -->
		<action name="PageAction_*" class="pageAction" method="{1}">
			<result name="addPagePage">/editPage.jsp</result>
			<!-- 设计调查 -->
			<result name="designSurveyAction" type="redirectAction">
				<param name="namespace"></param>
				<param name="actionName">SurveyAction_designSurvey</param>
				<param name="sid">${sid}</param>
			</result>
			<result name="editPage">/editPage.jsp</result>
		</action>
		
		<!-- QuestionAction -->
		<action name="QuestionAction_*" class="questionAction" method="{1}">
			<result name="selectQuestionTypePage">/selectQuestionType.jsp</result>
			<!-- 根据题型动态返回设计问题页面 总共九类问题-->
			<result name="0">/nonMatrixWithOtherQuestionDesign.jsp</result>
			<result name="1">/nonMatrixWithOtherQuestionDesign.jsp</result>
			<result name="2">/nonMatrixWithOtherQuestionDesign.jsp</result>
			<result name="3">/nonMatrixWithOtherQuestionDesign.jsp</result>
			<result name="4">/nonMatrixSelectQuestionDesign.jsp</result>
			<result name="5">/nonMatrixTextQuestionDesign.jsp</result>
			<result name="6">/matrixNormalQuestionDesign.jsp</result>
			<result name="7">/matrixNormalQuestionDesign.jsp</result>
			<result name="8">/matrixSelectQuestionDesign.jsp</result>
			<result name="designSurveyAction" type="redirectAction">
				<param name="namespace"></param>
				<param name="actionName">SurveyAction_designSurvey</param>
				<param name="sid">${sid}</param>
			</result>
		</action>
		
		<action name="MoveOrCopyPageAction_*" class="moveOrCopyPageAction" method="{1}">
			<result name="moveOrCopyPageListPage">/moveOrCopyPageList.jsp</result>
		</action>
		
	</package>
</struts>
